cybersecurity_log_generator/__init__.py
cybersecurity_log_generator/__main__.py
cybersecurity_log_generator/advanced_attack_data_ingestor.py
cybersecurity_log_generator/api.py
cybersecurity_log_generator/apt29_campaign.json
cybersecurity_log_generator/apt29_campaign_100.json
cybersecurity_log_generator/attack_data_config.yaml
cybersecurity_log_generator/attack_data_ingestor.py
cybersecurity_log_generator/claude_desktop_config.json
cybersecurity_log_generator/claude_desktop_config_remote.json
cybersecurity_log_generator/claude_desktop_config_remote_stdio.json
cybersecurity_log_generator/cli.py
cybersecurity_log_generator/complete_attack_data_ingestor.py
cybersecurity_log_generator/comprehensive_test_suite.py
cybersecurity_log_generator/config.py
cybersecurity_log_generator/config.yaml
cybersecurity_log_generator/continuous_upload.py
cybersecurity_log_generator/crewai_config.yaml
cybersecurity_log_generator/crewai_cybersecurity_crew.py
cybersecurity_log_generator/crewai_ollama_correct_llm_test_report.json
cybersecurity_log_generator/crewai_ollama_final_test_report.json
cybersecurity_log_generator/crewai_ollama_mcp_connection_test_report.json
cybersecurity_log_generator/crewai_ollama_mcp_fixed_test_report.json
cybersecurity_log_generator/crewai_ollama_mcp_test_report.json
cybersecurity_log_generator/crewai_ollama_working_test_report.json
cybersecurity_log_generator/cursor_mcp_config.json
cybersecurity_log_generator/cursor_mcp_config_remote.json
cybersecurity_log_generator/cursor_mcp_config_remote_stdio.json
cybersecurity_log_generator/demo.py
cybersecurity_log_generator/deploy.py
cybersecurity_log_generator/docker-compose.http.yml
cybersecurity_log_generator/docker-compose.remote.yml
cybersecurity_log_generator/docker-compose.yml
cybersecurity_log_generator/endpoint_logs_100.json
cybersecurity_log_generator/enhanced_demo.py
cybersecurity_log_generator/firewall_intrusion_logs_10.json
cybersecurity_log_generator/firewall_logs_10.json
cybersecurity_log_generator-1.0.1.dist-info/licenses/LICENSE
cybersecurity_log_generator-1.0.1.dist-info/METADATA
cybersecurity_log_generator-1.0.1.dist-info/WHEEL
cybersecurity_log_generator-1.0.1.dist-info/entry_points.txt
cybersecurity_log_generator-1.0.1.dist-info/top_level.txt
cybersecurity_log_generator-1.0.1.dist-info/RECORD
