Metadata-Version: 2.4
Name: cybersecurity-log-generator
Version: 1.0.1
Summary: Generate synthetic cybersecurity logs for testing and analysis across all 24 cyberdefense pillars
Home-page: https://github.com/tredkar/hd-syntheticdata
Author: Cybersecurity Log Generator Team
Author-email: Cybersecurity Log Generator Team <support@cybersecurity-log-generator.com>
License: MIT
Project-URL: Homepage, https://github.com/tredkar/hd-syntheticdata
Project-URL: Documentation, https://github.com/tredkar/hd-syntheticdata/blob/main/README.md
Project-URL: Repository, https://github.com/tredkar/hd-syntheticdata
Project-URL: Bug Reports, https://github.com/tredkar/hd-syntheticdata/issues
Keywords: cybersecurity,log generation,security testing,synthetic data,threat simulation,SIEM,SOC,security analysis,penetration testing,red team,blue team
Classifier: Development Status :: 4 - Beta
Classifier: Intended Audience :: Developers
Classifier: Intended Audience :: Information Technology
Classifier: Topic :: Security
Classifier: Topic :: Software Development :: Testing
Classifier: License :: OSI Approved :: MIT License
Classifier: Programming Language :: Python :: 3
Classifier: Programming Language :: Python :: 3.8
Classifier: Programming Language :: Python :: 3.9
Classifier: Programming Language :: Python :: 3.10
Classifier: Programming Language :: Python :: 3.11
Classifier: Programming Language :: Python :: 3.12
Requires-Python: >=3.8
License-File: LICENSE
Requires-Dist: fastmcp>=0.1.0
Requires-Dist: faker>=20.0.0
Requires-Dist: requests>=2.28.0
Requires-Dist: pydantic>=2.0.0
Requires-Dist: uvicorn>=0.20.0
Requires-Dist: python-dotenv>=1.0.0
Provides-Extra: dev
Requires-Dist: pytest>=7.0.0; extra == "dev"
Requires-Dist: pytest-cov>=4.0.0; extra == "dev"
Requires-Dist: black>=22.0.0; extra == "dev"
Requires-Dist: flake8>=5.0.0; extra == "dev"
Requires-Dist: mypy>=1.0.0; extra == "dev"
Provides-Extra: mcp
Requires-Dist: fastmcp>=0.1.0; extra == "mcp"
Provides-Extra: api
Requires-Dist: fastapi>=0.100.0; extra == "api"
Requires-Dist: uvicorn>=0.20.0; extra == "api"
Dynamic: author
Dynamic: home-page
Dynamic: license-file
Dynamic: requires-python
